store_var/__init__.py
store_var/store_var.py
store_var-1.dist-info/METADATA
store_var-1.dist-info/WHEEL
store_var-1.dist-info/licenses/LICENSE
store_var-1.dist-info/RECORD
