Metadata-Version: 2.1
Name: store_var
Version: 1
Summary: List wrapper, that pickles it on every update
Project-URL: Github, https://github.com/zahrevsky/store_var
Author-email: Vlad Zahrevsky <zahrevsky@gmail.com>
License-File: LICENSE
Classifier: License :: OSI Approved :: MIT License
Classifier: Operating System :: OS Independent
Classifier: Programming Language :: Python :: 3
Requires-Python: >=3.8
